crewai_adapters/__init__.py
crewai_adapters/base.py
crewai_adapters/client.py
crewai_adapters/context_protocol.py
crewai_adapters/exceptions.py
crewai_adapters/tools.py
crewai_adapters/types.py
crewai_adapters/utils.py
crewai_adapters/adapters/__init__.py
crewai_adapters/adapters/basic.py
crewai_adapters-0.1.2.dist-info/LICENSE
crewai_adapters-0.1.2.dist-info/METADATA
crewai_adapters-0.1.2.dist-info/WHEEL
crewai_adapters-0.1.2.dist-info/top_level.txt
crewai_adapters-0.1.2.dist-info/RECORD
